aigverse/CMakeLists.txt
aigverse/__init__.py
aigverse/_version.py
aigverse/_version.pyi
aigverse/aigverse.cpp
aigverse/pch.hpp
aigverse/py.typed
aigverse/pyaigverse.cpython-310-aarch64-linux-gnu.so
aigverse/pyaigverse.pyi
aigverse/adapters/__init__.py
aigverse/adapters/edge_list.cpp
aigverse/adapters/index_list.cpp
aigverse/adapters/networkx.py
aigverse/algorithms/balancing.cpp
aigverse/algorithms/equivalence_checking.cpp
aigverse/algorithms/refactoring.cpp
aigverse/algorithms/resubstitution.cpp
aigverse/algorithms/rewriting.cpp
aigverse/algorithms/simulation.cpp
aigverse/io/read_aiger.cpp
aigverse/io/read_pla.cpp
aigverse/io/read_verilog.cpp
aigverse/io/write_aiger.cpp
aigverse/io/write_dot.cpp
aigverse/io/write_verilog.cpp
aigverse/networks/logic_networks.cpp
aigverse/truth_tables/operations.cpp
aigverse/truth_tables/truth_table.cpp
aigverse-0.0.25.dist-info/METADATA
aigverse-0.0.25.dist-info/WHEEL
aigverse-0.0.25.dist-info/RECORD
aigverse-0.0.25.dist-info/licenses/LICENSE
