Metadata-Version: 2.1
Name: aigverse
Version: 0.0.25
Summary: A Python library for working with logic networks, synthesis, and optimization.
Keywords: aigverse,logic,synthesis,AIG,EDA,optimization,machine learning,artificial intelligence
Author-Email: Marcel Walter <marcel.walter@tum.de>
License: MIT License
Classifier: Development Status :: 4 - Beta
Classifier: Programming Language :: C++
Classifier: Programming Language :: Python :: 3
Classifier: Programming Language :: Python :: 3 :: Only
Classifier: Programming Language :: Python :: 3.9
Classifier: Programming Language :: Python :: 3.10
Classifier: Programming Language :: Python :: 3.11
Classifier: Programming Language :: Python :: 3.12
Classifier: Programming Language :: Python :: 3.13
Classifier: Programming Language :: Python :: 3.14
Classifier: License :: OSI Approved :: MIT License
Classifier: Operating System :: Microsoft :: Windows
Classifier: Operating System :: MacOS
Classifier: Operating System :: POSIX :: Linux
Classifier: Intended Audience :: Science/Research
Classifier: Natural Language :: English
Classifier: Topic :: Scientific/Engineering :: Electronic Design Automation (EDA)
Classifier: Typing :: Typed
Project-URL: Source, https://github.com/marcelwa/aigverse
Project-URL: Tracker, https://github.com/marcelwa/aigverse/issues
Project-URL: Documentation, https://aigverse.readthedocs.io/en/latest/
Requires-Python: >=3.9
Provides-Extra: adapters
Requires-Dist: networkx>=3.0.0; extra == "adapters"
Requires-Dist: numpy>=1.23.0; extra == "adapters"
